{
    "135233": "训练基地",
    "153443": "火箭掠影",
    "135260": "黄金导弹车",
    "803050": "提升坦克英雄战斗力",
    "season_person_building_name010": "导弹基地",
    "135231": "冶炼厂",
    "item_name_707007": "鲜血王座",
    "801196": "警戒塔",
    "129058": "商店",
    "building_desc_new103518000": "建设这个装饰物，让可爱的小熊为情人们送上有节日气息的气球和花朵。",
    "item_name_707401": "星空望远镜",
    "135118": "炮台",
    "135119": "科技中心",
    "135151": "只要有合适的材料，铁匠就可以制造出合适的装备。提升等级可以解锁更高级的制造配方。",
    "129035": "飞机中心",
    "800351": "第一小队",
    "building_desc_new103421000": "冰凉丰富多彩，快乐锦上添花。",
    "building_desc_new103528000": "传递薪火，点燃希望",
    "803047": "提高部队的病毒抗性",
    "135104": "总部",
    "135155": "基地外面的世界很危险，需要外出的幸存者都需要准备好装备和载具。停车场都是外出部队的专属车位。",
    "180028": "末世上遗留的不知名遗物，可在雷达探测中获得",
    "143638": "143638",
    "season_person_building_name775000": "钛合金工厂周卡",
    "135114": "校场",
    "building_desc_new103203000": "一只姿态高傲的火烈鸟雕像，展翅欲飞，静默中散发着炽热的活力。",
    "135108": "铁矿仓库",
    "135109": "金矿",
    "135246": "椰树",
    "building_desc_new103501000": "黄金铸造的坦克，象征着坦克英雄的勇气与力量。",
    "135236": "产出装备制造材料",
    "457504": "世界陷入了混乱，土地荒芜，城市破败。在这个战火纷飞的时代，人们为了生存和繁荣而不断寻求资源，贸易成为了最重要的获取资源的方式。",
    "building_desc_10220000": "用于提升幸存者能力",
    "135253": "青铜飞机",
    "130167": "130167",
    "135202": "武装货车",
    "135147": "谁也不想生吃小麦，但没有人能拒绝用小麦面粉做出的面包，耐饱口感也不错。提升等级可以增加面包的产量",
    "building_desc_10218000": "用于指挥官选择职业和管理职业天赋。",
    "135254": "和平主义",
    "building_desc_new103512000": "2024新年快乐！",
    "135139": "提升科技水平",
    "season_building_desc745000": "全面提升飞机英雄在赛季期间的的战斗实力！",
    "season_s2_building_description02": "强化飞机英雄",
    "135157": "可以配置防守的幸存者，抵挡敌人的入侵。",
    "building_desc10232000": "building_desc10232000",
    "building_name_10220000": "人才大厅",
    "building_name10232000": "芯片研究所",
    "457503": "贸易车站",
    "129037": "建筑工小屋",
    "building_desc_new103521000": "我们放下烦恼，复活欢乐；我们抛开忧愁，复活笑容；我们齐聚一堂，让友谊长存；我们传递希望，让你不再随遇漂流。复活节快乐！",
    "building_desc_new103201000": "优雅而舒适的长椅，为基地增添魅力。",
    "500475": "人们用它来记述丰功伟业",
    "129032": "增加坦克对导弹的克制",
    "season_building_name765000": "蛋白农场Ⅳ",
    "building_desc_new103403000": "白银铸造的坦克，象征着坦克英雄的勇气与力量。",
    "121028": "完成雷达探测任务，可获得包括招募券在内的丰厚奖励。",
    "135156": "可以让您更方便的与盟友交流，同时也能获得来自盟友的援助与礼物。",
    "135234": "产出英雄经验",
    "135259": "黄金坦克",
    "800837": "光鲜、亮丽、庄严、不容玷污！",
    "135124": "正如其名，您的总部",
    "building_name_10234000": "第3科研中心",
    "135106": "铁矿场",
    "building_desc_new103508000": "五彩斑斓的霓虹灯牌，闪耀着绚烂的光芒，为夜晚增添了一抹迷人的色彩。",
    "season_building_name761000_new": "蛋白农场Ⅰ",
    "building_desc_new103301000": "青铜铸造的坦克，象征着坦克英雄的勇气与力量。",
    "building_desc_new103507000": "高耸入云，彩灯闪烁，载着人们徐徐旋转，带来无尽的欢乐与刺激。",
    "135257": "白银毁灭者",
    "135235": "材料车间",
    "135145": "不太肥沃的土地，只能种种小麦，但在这末世我们不能要求更多。提升等级后可以增加小麦的产量。",
    "season_person_building_name774000": "钛合金工厂4号",
    "2000575": "生产1级无人机组件宝箱",
    "320000": "320000",
    "season_person_building_name006": "沙漠医院",
    "item_name705901": "情意漫漫",
    "135126": "挖掘铁矿石",
    "building_desc_new103517000": "新春福气临门，快把这只新年龙建设在主城内，为你带来财运吧！",
    "season_building_desc757000": "全面提升导弹英雄在赛季期间的的战斗实力！",
    "129042": "升级减少免费抽卡间隔",
    "135251": "青铜坦克",
    "building_desc_new103513000": "华丽的黄金装饰品，展示着权威与荣耀。",
    "803052": "提升导弹英雄战斗力",
    "135107": "粮食仓库",
    "135245": "桦树",
    "season_person_building_name009": "空军基地",
    "building_desc_new103417000": "熊熊燃烧的战斗舞台，充满力量与激情！",
    "800352": "第二小队",
    "season_person_building_name005": "土地规划局",
    "2000755": "第1科研中心",
    "building_desc_new103523000": "在探险中发现的这块蓝色石碑，为指挥官在末世中谱写勇气的赞歌。",
    "135112": "收容所",
    "item_name103513000": "黄金元帅雕像",
    "building_name10224000": "building_name10224000",
    "800836": "军旗",
    "135268": "吓坏了",
    "135198": "猎鹰搜救队",
    "building_desc_new103503000": "黄金铸造的飞机，象征着飞机英雄的勇气与力量。",
    "season_person_building_name773000": "钛合金工厂3号",
    "building_desc_new103302000": "青铜铸造的导弹车，象征着导弹英雄的勇气与力量。",
    "803049": "增加部队带兵量",
    "building_desc_new103502000": "黄金铸造的导弹车，象征着导弹英雄的勇气与力量。",
    "135163": "雷达能为我们提供侦察单位，升级雷达中心可以提高侦察速度，一定等级后还能增加侦察单位。",
    "135133": "训练士兵",
    "building_desc_new103526000": "传承经典，旋律永恒，交互可收听一段神秘音乐。",
    "135264": "铁塔复制品",
    "season_person_building_desc771000": "用于生产钛合金",
    "135243": "榆树",
    "building_desc_new103511000": "装饰多彩灯，挂满闪亮星，散发温暖气息。",
    "building_name10219000": "装饰物收藏馆",
    "135270": "无人机中心",
    "item_name_706301": "欢乐萌兔",
    "building_desc_new103202000": "水柱飞溅、清凉流淌，传说向其中投入硬币可以许愿。",
    "801121": "竞技场",
    "building_desc_new103418000": "英勇的士兵，永远冲锋在最前线，他们的牺牲值得纪念。",
    "135154": "我的士兵都会在校场进行集合，随时准备战斗。提升校场等级可以提升士兵的数量上限。",
    "item_name103417000": "item_name103417000",
    "457558": "贸易车队-3",
    "season_person_building_long_desc771000": "season_person_building_long_desc771000",
    "135146": "一座铁矿，能够从中获得源源不断的铁矿石。提升等级后可以增加铁矿石的产量。",
    "season_s2_building_description03": "强化导弹英雄",
    "135255": "它是传奇",
    "season_building_desc743000": "破坏中心能够提升部队的破坏值属性；\\n让部队在破坏其他指挥官基地、城市耐久值时造成更多伤害！",
    "building_detailed desc_10231000": "战斗中的阵亡的士兵应该还能够抢救一下，尽管只是一部分",
    "item_name_707005": "审判之神",
    "457556": "贸易车队-2",
    "135252": "青铜炮车",
    "item_name_707301": "漫游月球",
    "season_building_name762000": "蛋白农场Ⅱ",
    "135263": "自由女神",
    "season_person_building_name001": "病毒研究所I",
    "building_desc_new103515000": "象征着辉煌的胜利与无限的力量。",
    "item_name706021": "永恒金字塔",
    "item_name_706501": "美味冰淇淋",
    "building_desc10223000": "黑市商人的房车，记得去逛逛哦，不然可就开走啦！",
    "100728": "可以研究科技，提升基地能力",
    "143636": "143636",
    "135265": "摩天轮",
    "building_desc_10233000": "用于生产无人机零件",
    "item_name705101": "干杯火鸡",
    "item_name_706801": "黄金机动队",
    "item_name_706701": "勇士丰碑",
    "item_name103514000": "军功纪念碑",
    "season_person_building_desc761000": "用于从植物中提取免疫蛋白。",
    "season_person_building_name770000": "高温熔炉",
    "129028": "挖金矿",
    "135258": "白银火箭",
    "item_name707004": "银色炮兵",
    "800798": "钢筋混泥土结构，足以支持任何大型单位！",
    "457555": "人们为了生存和繁荣而不断寻求资源，贸易车队成为了最重要的贸易和交通方式。",
    "135113": "兵营",
    "building_desc_new103509000": "南瓜头，悠闲微笑，在烛光下，变幻出恐怖的影子。",
    "building_desc_new103413000": "英勇的士兵，永远冲锋在最前线，他们的牺牲值得纪念。",
    "item_name_706901": "美妙留声机",
    "135135": "出征部队的专属车位",
    "building_name_10221000": "油井",
    "building_name103405000": "圣诞雪人",
    "season_building_info753000": "降低赛季期间土地战斗重伤率",
    "135271": "加强战术无人机",
    "135131": "制造装备",
    "season_person_building_name002": "病毒研究所II",
    "2000574": "无人机组件工厂",
    "143620": "143620",
    "building_desc10219000": "在这里查看你的装饰物收集进度吧！",
    "item_name_707501": "恶作剧杰克",
    "135232": "产出强化石",
    "129036": "增加飞机对坦克的克制",
    "item_name705701": "吉日祥天",
    "building_desc_new103524000": "黄金铸造的丰碑，表彰机动队勇敢与忠诚的信念",
    "135136": "同盟帮助功能",
    "143665": "143665",
    "building_desc_new103510000": "金黄诱人，香气四溢，是丰收的节日。",
    "building_desc103516000": "蕴含神秘力量的古代遗迹，可以永久提升建筑速度。",
    "135256": "白银战机",
    "135242": "银杏树",
    "season_building_desc753000": "沙漠医院能够减少土地战斗的士兵损失；\\n医疗保障必不可少。",
    "800353": "第三小队",
    "building_desc_new103402000": "白银铸造的飞机，象征着飞机英雄的勇气与力量。",
    "135153": "兵营能为基地源源不断的训练士兵。提升兵营等级能够提升每次训练士兵的数量，同时能够解锁训练更高级的士兵。",
    "156040": "雷达车",
    "item_name_707201": "火炬速递",
    "135111": "装备工厂",
    "season_person_building_desc770000": "能够同时提升病毒抗性和所在地温度",
    "building_desc_10231000": "抢救更多濒危士兵",
    "item_name_706401": "复活节彩蛋",
    "building_desc_new103416000": "悠悠钟声，万象更新，建设这个装饰物来迎接新年吧！",
    "building_desc_new103404000": "白银铸造的导弹车，象征着导弹英雄的勇气与力量。",
    "building_name_10218000": "职业大厅",
    "building_desc_new103424000": "漫天繁星，带来无尽希望与灵感。",
    "season_person_building_name764000": "蛋白农场(赛季周卡专属）",
    "item_name_706201": "春意盎然",
    "129034": "增加导弹对飞机的克制",
    "season_building_desc741000": "是赛季期间的重要建筑，用于提升部队的病毒抗性；\\n提升病毒抗性是占领更高级被污染的土地的前提；\\n建议优先升级！",
    "season_building_desc744000": "全面提升坦克英雄在赛季期间的的战斗实力！",
    "building_desc_new103405000": "胖嘟嘟的身上系着彩色围巾，给人温暖与喜悦。",
    "item_name_707006": "银色突击手",
    "building_desc_new103519000": "春临大地，生机盎然",
    "135266": "霓虹灯牌",
    "135150": "炼钢厂可以将铁矿石进行提纯熔炼，得到重要的建筑材料铁矿。提升等级可以增加铁矿获得量",
    "135138": "可以保护我们的基地",
    "135249": "幸运水池",
    "135158": "基地遭受攻击时，炮台能够提供可靠的火力支援。",
    "135143": "持续收集资源",
    "season_person_building_name007": "破坏研究所",
    "457560": "贸易车队-Ω",
    "129033": "导弹中心",
    "129029": "金币仓库",
    "135134": "士兵集合地点",
    "135144": "总部是基地的核心。等级越高可以解锁更多的建筑类型，同时也会提升其他建筑的等级上限和英雄等级。",
    "800365": "侦察机",
    "item_name103515000": "胜利之塔",
    "building_desc10224000": "building_desc10224000",
    "500474": "纪念碑",
    "building_name103413000": "银白战士",
    "season_person_building_name003": "病毒研究所III",
    "building_desc_new103420000": "英勇的突击手，冲破防线，让敌人溃不成军。",
    "item_name_707101": "疯狂节拍",
    "building_desc_10221000": "用于生产石油",
    "building_desc_new103401000": "忠诚而无私，永远守护着主人。",
    "building_name103511000": "缤纷圣诞树",
    "building_name_10233000": "无人机零件车间",
    "item_name103414000": "特训轮胎",
    "season_s2_building_description01": "强化坦克英雄",
    "building_desc_new103530000": "building_desc_new103530000",
    "135200": "完成搜救任务，获得丰厚奖励",
    "129041": "酒馆",
    "item_name_706601": "芝心庄园",
    "135105": "农田",
    "season_building_desc742000": "用于增加占领土地的数量上限；\\n拥有更多的土地可以获得更多的赛季资源产量；\\n建议优先升级！",
    "135140": "治疗重伤士兵",
    "dispatch_des030": "每日发布隐秘任务，完成任务收获大量奖励",
    "building_desc_new103414000": "特种部队常用的训练工具，如同士兵的意志一般坚韧耐磨。",
    "135248": "长椅",
    "135199": "特别行动小队专用座驾！",
    "135127": "保护一定数量的粮食不被掠夺",
    "building_name_10231000": "急救中心",
    "135125": "种植小麦",
    "building_desc_new103506000": "优雅的曲线勾勒出浪漫的城市天际线。",
    "building_desc_new103204000": "枝叶繁茂，散发着太阳般的光辉。",
    "100308": "路",
    "135120": "医院",
    "building_desc_new103522000": "芝有用心，留您芳心，美食节快乐！",
    "135137": "配置防守部队",
    "143635": "143635",
    "season_person_building_name004": "病毒研究所IV",
    "803051": "提升飞机英雄战斗力",
    "801197": "先进的雷达武器，能够侦测到向您的基地行军中的部队。",
    "457554": "贸易车队-1",
    "135116": "同盟中心",
    "building_desc_new103520000": "古老帝国的神灵，据说会通过心脏的重量，对亡魂进行审判。",
    "135250": "火烈鸟雕像",
    "129040": "增加免费时间",
    "800797": "英雄平台",
    "building_desc_new103525000": "只有接受血珀之赐的人，才能坐上鲜血王座。",
    "135128": "保护一定数量的铁矿不被掠夺",
    "building_desc_new103505000": "高耸傲立，手握火炬，眼神坚定，象征着自由与希望。",
    "129030": "保护一定数量的金币不被掠夺",
    "135132": "一个温馨的家",
    "building_name10223000": "黑市商店",
    "135244": "橡树",
    "135117": "城墙",
    "801122": "指挥官之间进行模拟演习的地方！",
    "building_desc_new103516000": "来自久远沙漠的奇迹，散发着神秘文明的魅力。",
    "135152": "温馨而又住所，拥有优质的生活配置，能够容纳不少幸存者。提升等级可以增加幸存者的容纳人数。",
    "135262": "钟楼",
    "building_name103512000": "赢在2024",
    "135129": "挖取金币",
    "season_person_building_name771000": "钛合金工厂1号",
    "building_desc_new103423000": "止不住的疯狂，停不了的节拍，为胜利欢呼，为爱情鼓掌。",
    "2000756": "第2科研中心",
    "building_desc_new103303000": "青铜铸造的飞机，象征着飞机英雄的勇气与力量。",
    "129031": "坦克中心",
    "129059": "使用货币兑换各种需要的道具",
    "season_person_building_name772000": "钛合金工厂2号",
    "dispatch_des029": "隐秘指挥所",
    "season_person_building_long_desc770000": "season_person_building_long_desc770000",
    "season_person_building_name008": "坦克基地",
    "building_desc_new103304000": "希望这个世界再没有战争。",
    "building_desc_new103529000": "月亮之下，梦想无垠。触摸星辰，拥抱未来。",
    "building_desc_new103419000": "希望常在，绽放美丽风采。复活节快乐！",
    "135261": "黄金轰炸机",
    "803048": "增加占领土地上限",
    "item_name705801": "迎新送福",
    "building_desc_new103514000": "巍峨挺拔，军功辉煌，铭刻着英勇战士们的壮丽荣耀。",
    "800354": "第四小队",
    "building_desc_new103504000": "它宛如守望者，静静守护着时光的流转。",
    "season_building_name763000": "蛋白农场Ⅲ",
    "143637": "143637"
}